citty.py
citty-0.0.3.dist-info/entry_points.txt
citty-0.0.3.dist-info/LICENSE
citty-0.0.3.dist-info/WHEEL
citty-0.0.3.dist-info/METADATA
citty-0.0.3.dist-info/RECORD
