Metadata-Version: 2.1
Name: citty
Version: 0.0.3
Summary: citty -- CI driver in your terminal.
Home-page: https://gitlab.com/aghast/citty/
License: UNKNOWN
Author: aghast
Author-email: aghast@aghast.dev
Requires-Python: >=3.6
Classifier: Development Status :: 3 - Alpha
Classifier: Environment :: Console
Classifier: Intended Audience :: Developers
Classifier: License :: OSI Approved :: GNU General Public License v3 or later (GPLv3+)
Classifier: Programming Language :: Python :: 3
Classifier: Programming Language :: Python :: 3.6
Classifier: Topic :: Software Development :: Build Tools
Classifier: Topic :: Software Development :: Testing
Requires-Dist: docopt-ng
Requires-Dist: pytest ; extra == "test"
Project-URL: Documentation, https://gitlab.com/aghast/citty/-/blob/master/README.md#name
Project-URL: Source Code, https://gitlab.com/aghast/citty/
Provides-Extra: test
